dcoshelpers/dcosjwt.py
dcoshelpers-0.5.4.dist-info/LICENSE
dcoshelpers-0.5.4.dist-info/METADATA
dcoshelpers-0.5.4.dist-info/WHEEL
dcoshelpers-0.5.4.dist-info/top_level.txt
dcoshelpers-0.5.4.dist-info/RECORD
